sap2000_mcp/__init__.py
sap2000_mcp/__main__.py
sap2000_mcp/manager.py
sap2000_mcp/server.py
sap2000_mcp-0.1.0.dist-info/licenses/LICENSE
sap2000_mcp-0.1.0.dist-info/METADATA
sap2000_mcp-0.1.0.dist-info/WHEEL
sap2000_mcp-0.1.0.dist-info/entry_points.txt
sap2000_mcp-0.1.0.dist-info/top_level.txt
sap2000_mcp-0.1.0.dist-info/RECORD
