Metadata-Version: 2.4
Name: sap2000-mcp
Version: 0.1.0
Summary: Minimal MCP server to operate SAP2000 from AI agents
Author: Kazem
License: MIT
Requires-Python: >=3.10
License-File: LICENSE
Requires-Dist: mcp>=1.0.0
Requires-Dist: comtypes>=1.4.0
Dynamic: author
Dynamic: description
Dynamic: description-content-type
Dynamic: license
Dynamic: license-file
Dynamic: requires-dist
Dynamic: requires-python
Dynamic: summary
